fand/__init__.py
fand/clientrpi.py
fand/communication.py
fand/exceptions.py
fand/fanctl.py
fand/server.py
fand/util.py
fand-0.1.0.data/scripts/fand
fand-0.1.0.dist-info/LICENSE
fand-0.1.0.dist-info/METADATA
fand-0.1.0.dist-info/WHEEL
fand-0.1.0.dist-info/entry_points.txt
fand-0.1.0.dist-info/top_level.txt
fand-0.1.0.dist-info/RECORD
