Metadata-Version: 2.1
Name: fand
Version: 0.1.0
Summary: Simple daemon to control fan speed
Home-page: https://github.com/lleseur/fand
Author: Louis Leseur
Author-email: louis.leseur@gmail.com
License: MIT
Keywords: fan-control,daemon,hardware,raspberry-pi,gpio,monitoring,temperature-monitoring,pysmart,gpiozero
Platform: UNKNOWN
Classifier: Development Status :: 3 - Alpha
Classifier: Environment :: No Input/Output (Daemon)
Classifier: Intended Audience :: System Administrators
Classifier: License :: OSI Approved :: MIT License
Classifier: Operating System :: POSIX
Classifier: Programming Language :: Python
Classifier: Programming Language :: Python :: 3
Classifier: Programming Language :: Python :: 3.6
Classifier: Programming Language :: Python :: 3.7
Classifier: Programming Language :: Python :: 3.8
Classifier: Programming Language :: Python :: Implementation :: CPython
Classifier: Programming Language :: Python :: Implementation :: PyPy
Classifier: Topic :: System :: Hardware
Classifier: Topic :: System :: Monitoring
Requires-Python: >=3, <4
Provides-Extra: clientrpi-pigpio
Requires-Dist: gpiozero ; extra == 'clientrpi-pigpio'
Requires-Dist: pigpio ; extra == 'clientrpi-pigpio'
Provides-Extra: clientrpi-rpi-gpio
Requires-Dist: gpiozero ; extra == 'clientrpi-rpi-gpio'
Requires-Dist: RPi.GPIO ; extra == 'clientrpi-rpi-gpio'
Provides-Extra: clientrpi-rpio
Requires-Dist: gpiozero ; extra == 'clientrpi-rpio'
Requires-Dist: RPIO ; extra == 'clientrpi-rpio'
Provides-Extra: doc
Requires-Dist: sphinx ; extra == 'doc'
Provides-Extra: server
Requires-Dist: pySMART ; extra == 'server'
Requires-Dist: psutil ; extra == 'server'
Provides-Extra: test
Requires-Dist: flake8 ; extra == 'test'
Requires-Dist: pytest ; extra == 'test'
Requires-Dist: tox ; extra == 'test'
Requires-Dist: mypy ; extra == 'test'
